eowriter/__init__.py
eowriter/eowriter.py
eowriter-0.1.5.dist-info/METADATA
eowriter-0.1.5.dist-info/WHEEL
eowriter-0.1.5.dist-info/top_level.txt
eowriter-0.1.5.dist-info/RECORD
