Metadata-Version: 2.1
Name: eowriter
Version: 0.1.5
Summary: write eo information.
Home-page: UNKNOWN
Author: Danian Hu
Author-email: hudanian@gmail.com
License: UNKNOWN
Platform: UNKNOWN
Requires-Dist: xlsxwriter
